{
  "app\\App.tsx": [],
  "app\\main.tsx": [],
  "components\\App.tsx": [],
  "components\\common\\AccessibilityComponents.tsx": [],
  "components\\common\\index.ts": [],
  "components\\index.ts": [],
  "components\\layout\\index.ts": [],
  "components\\layout\\PWABadge.tsx": [],
  "components\\map\\index.ts": [],
  "components\\map\\MapView\\index.ts": [],
  "components\\map\\MapView\\MapContainer.tsx": [],
  "components\\map\\MapView\\MapErrorFallback.tsx": [],
  "components\\map\\MapView\\MapInfoWindow.tsx": [],
  "components\\map\\MapView\\MapMarker.tsx": [],
  "components\\map\\MapView\\MapView.tsx": [],
  "components\\map\\MapView\\markerUtils.ts": [],
  "components\\map\\RestaurantMap.tsx": [],
  "components\\restaurant\\FilterPanel\\CuisineFilter.tsx": [],
  "components\\restaurant\\FilterPanel\\DistrictFilter.tsx": [],
  "components\\restaurant\\FilterPanel\\FilterChips.tsx": [],
  "components\\restaurant\\FilterPanel\\FilterPanel.tsx": [],
  "components\\restaurant\\FilterPanel\\index.ts": [],
  "components\\restaurant\\FilterPanel\\PriceFilter.tsx": [],
  "components\\restaurant\\FilterPanel\\SearchFilter.tsx": [],
  "components\\restaurant\\FilterPanel\\useFilterState.ts": [],
  "components\\restaurant\\FilterPanel.tsx": [],
  "components\\restaurant\\index.ts": [],
  "components\\restaurant\\ModernFilterPanel\\index.ts": [],
  "components\\restaurant\\ModernFilterPanel\\ModernCuisineFilter.tsx": [],
  "components\\restaurant\\ModernFilterPanel\\ModernDistrictFilter.tsx": [],
  "components\\restaurant\\ModernFilterPanel\\ModernFeatureFilter.tsx": [],
  "components\\restaurant\\ModernFilterPanel\\ModernFilterPanel.tsx": [],
  "components\\restaurant\\ModernFilterPanel\\ModernMapLegend.tsx": [],
  "components\\restaurant\\ModernFilterPanel\\ModernPriceFilter.tsx": [],
  "components\\restaurant\\ModernFilterPanel\\ModernSearchFilter.tsx": [],
  "components\\restaurant\\ModernFilterPanel\\useModernFilterState.ts": [],
  "config\\constants.ts": [],
  "config\\environment.ts": [],
  "config\\index.ts": [],
  "config\\types.ts": [],
  "hooks\\api\\index.ts": [],
  "hooks\\api\\useRestaurants.ts": [],
  "hooks\\index.ts": [],
  "hooks\\map\\index.ts": [],
  "hooks\\map\\useMapPoints.ts": [],
  "hooks\\ui\\index.ts": [],
  "hooks\\ui\\useAnalytics.ts": [],
  "hooks\\ui\\useErrorHandler.ts": [],
  "hooks\\useAnalytics.ts": [],
  "hooks\\useMapPoints.ts": [],
  "hooks\\useRestaurants.ts": [],
  "services\\index.ts": [],
  "services\\sheets\\index.ts": [],
  "services\\sheets\\sheetsService.ts": [],
  "services\\sheetsService.ts": [],
  "test\\setup.ts": [],
  "types\\api.types.ts": [],
  "types\\app.types.ts": [],
  "types\\core.types.ts": [],
  "types\\index.ts": [],
  "types\\map.types.ts": [],
  "types\\restaurant.types.ts": [],
  "types\\type-guards.ts": [],
  "types\\ui.types.ts": [],
  "utils\\analytics.ts": [],
  "utils\\district\\index.ts": [],
  "utils\\districtUtils.ts": [],
  "utils\\index.ts": [],
  "utils\\lightValidation.ts": [],
  "utils\\security\\index.ts": [],
  "utils\\securityUtils.ts": [],
  "utils\\validation\\environment.ts": [],
  "utils\\validation\\errors.ts": [],
  "utils\\validation\\formatters.ts": [],
  "utils\\validation\\guards.ts": [],
  "utils\\validation\\index.ts": [],
  "utils\\validation\\sanitizers.ts": [],
  "utils\\validationUtils.new.ts": [],
  "utils\\validationUtils.ts": []
}